LinuxMinglingDaquanLinuxtoday/README.md
LinuxMinglingDaquanLinuxtoday/__init__.py
LinuxMinglingDaquanLinuxtoday/__main__.py
LinuxMinglingDaquanLinuxtoday/file.epub
LinuxMinglingDaquanLinuxtoday/index.html
LinuxMinglingDaquanLinuxtoday/css/__init__.py
LinuxMinglingDaquanLinuxtoday/css/annotations.css
LinuxMinglingDaquanLinuxtoday/css/main.css
LinuxMinglingDaquanLinuxtoday/css/normalize.css
LinuxMinglingDaquanLinuxtoday/css/popup.css
LinuxMinglingDaquanLinuxtoday/font/__init__.py
LinuxMinglingDaquanLinuxtoday/font/fontello.eot
LinuxMinglingDaquanLinuxtoday/font/fontello.svg
LinuxMinglingDaquanLinuxtoday/font/fontello.ttf
LinuxMinglingDaquanLinuxtoday/font/fontello.woff
LinuxMinglingDaquanLinuxtoday/img/__init__.py
LinuxMinglingDaquanLinuxtoday/img/annotator-glyph-sprite.png
LinuxMinglingDaquanLinuxtoday/img/annotator-icon-sprite.png
LinuxMinglingDaquanLinuxtoday/img/apple-touch-icon.png
LinuxMinglingDaquanLinuxtoday/img/cancelfullscreen.png
LinuxMinglingDaquanLinuxtoday/img/close.png
LinuxMinglingDaquanLinuxtoday/img/fullscreen.png
LinuxMinglingDaquanLinuxtoday/img/loader.gif
LinuxMinglingDaquanLinuxtoday/img/menu-icon.png
LinuxMinglingDaquanLinuxtoday/img/save.png
LinuxMinglingDaquanLinuxtoday/img/saved.png
LinuxMinglingDaquanLinuxtoday/img/settings-s.png
LinuxMinglingDaquanLinuxtoday/img/settings.png
LinuxMinglingDaquanLinuxtoday/img/star.png
LinuxMinglingDaquanLinuxtoday/js/__init__.py
LinuxMinglingDaquanLinuxtoday/js/epub.js
LinuxMinglingDaquanLinuxtoday/js/epub.min.js
LinuxMinglingDaquanLinuxtoday/js/epub.min.map
LinuxMinglingDaquanLinuxtoday/js/hooks.min.js
LinuxMinglingDaquanLinuxtoday/js/hooks.min.map
LinuxMinglingDaquanLinuxtoday/js/reader.js
LinuxMinglingDaquanLinuxtoday/js/reader.js.map
LinuxMinglingDaquanLinuxtoday/js/reader.min.js
LinuxMinglingDaquanLinuxtoday/js/reader.min.map
LinuxMinglingDaquanLinuxtoday/js/hooks/__init__.py
LinuxMinglingDaquanLinuxtoday/js/hooks/extensions/__init__.py
LinuxMinglingDaquanLinuxtoday/js/hooks/extensions/highlight.js
linux_mingling_daquan_linuxtoday-2024.3.3.0.dist-info/METADATA
linux_mingling_daquan_linuxtoday-2024.3.3.0.dist-info/WHEEL
linux_mingling_daquan_linuxtoday-2024.3.3.0.dist-info/entry_points.txt
linux_mingling_daquan_linuxtoday-2024.3.3.0.dist-info/top_level.txt
linux_mingling_daquan_linuxtoday-2024.3.3.0.dist-info/RECORD
